llmfeedback/__init__.py
llmfeedback/client.py
llm_feedback_client-0.1.dist-info/LICENSE
llm_feedback_client-0.1.dist-info/METADATA
llm_feedback_client-0.1.dist-info/WHEEL
llm_feedback_client-0.1.dist-info/top_level.txt
llm_feedback_client-0.1.dist-info/RECORD
